{
  "meta": {
    "sport": "hiking",
    "start_time": "2025-07-27T15:45:00Z",
    "end_time": "2025-07-27T16:00:58Z",
    "total_distance_m": 714.18,
    "total_elapsed_time_s": 958.0
  },
  "first_lat": 41.9396464,
  "first_lon": -82.5156261,
  "first_timestamp": "2025-07-27T15:45:00Z",
  "point_count": 96,
  "track": [
    {
      "lat": 41.9396464,
      "lon": -82.5156261,
      "t": "2025-07-27T15:45:00Z",
      "alt": 174.0
    },
    {
      "lat": 41.939609,
      "lon": -82.5156775,
      "t": "2025-07-27T15:45:10Z",
      "alt": 174.1
    },
    {
      "lat": 41.9394964,
      "lon": -82.515726,
      "t": "2025-07-27T15:45:20Z",
      "alt": 174.3
    },
    {
      "lat": 41.9394897,
      "lon": -82.5156483,
      "t": "2025-07-27T15:45:30Z",
      "alt": 174.4
    },
    {
      "lat": 41.9393875,
      "lon": -82.5156858,
      "t": "2025-07-27T15:45:40Z",
      "alt": 174.6
    },
    {
      "lat": 41.9392702,
      "lon": -82.5157002,
      "t": "2025-07-27T15:45:50Z",
      "alt": 174.7
    },
    {
      "lat": 41.9392675,
      "lon": -82.5157384,
      "t": "2025-07-27T15:46:00Z",
      "alt": 174.8
    },
    {
      "lat": 41.9392845,
      "lon": -82.515799,
      "t": "2025-07-27T15:46:10Z",
      "alt": 175.0
    },
    {
      "lat": 41.9392276,
      "lon": -82.5158115,
      "t": "2025-07-27T15:46:20Z",
      "alt": 175.1
    },
    {
      "lat": 41.9392389,
      "lon": -82.5159232,
      "t": "2025-07-27T15:46:30Z",
      "alt": 175.2
    },
    {
      "lat": 41.9391658,
      "lon": -82.5160668,
      "t": "2025-07-27T15:46:40Z",
      "alt": 175.3
    },
    {
      "lat": 41.939146,
      "lon": -82.5160759,
      "t": "2025-07-27T15:46:50Z",
      "alt": 175.3
    },
    {
      "lat": 41.9392034,
      "lon": -82.5161367,
      "t": "2025-07-27T15:47:01Z",
      "alt": 175.4
    },
    {
      "lat": 41.9391617,
      "lon": -82.5161459,
      "t": "2025-07-27T15:47:11Z",
      "alt": 175.4
    },
    {
      "lat": 41.9392065,
      "lon": -82.5161123,
      "t": "2025-07-27T15:47:21Z",
      "alt": 175.5
    },
    {
      "lat": 41.9391042,
      "lon": -82.5161325,
      "t": "2025-07-27T15:47:31Z",
      "alt": 175.5
    },
    {
      "lat": 41.9391288,
      "lon": -82.5162028,
      "t": "2025-07-27T15:47:41Z",
      "alt": 175.5
    },
    {
      "lat": 41.9391072,
      "lon": -82.5162163,
      "t": "2025-07-27T15:47:51Z",
      "alt": 175.5
    },
    {
      "lat": 41.9390534,
      "lon": -82.5162758,
      "t": "2025-07-27T15:48:01Z",
      "alt": 175.5
    },
    {
      "lat": 41.9390455,
      "lon": -82.5163415,
      "t": "2025-07-27T15:48:11Z",
      "alt": 175.4
    },
    {
      "lat": 41.9390136,
      "lon": -82.5163949,
      "t": "2025-07-27T15:48:21Z",
      "alt": 175.4
    },
    {
      "lat": 41.9390613,
      "lon": -82.5164612,
      "t": "2025-07-27T15:48:31Z",
      "alt": 175.3
    },
    {
      "lat": 41.940199,
      "lon": -82.5159017,
      "t": "2025-07-27T15:48:41Z",
      "alt": 175.2
    },
    {
      "lat": 41.9401343,
      "lon": -82.5159787,
      "t": "2025-07-27T15:48:51Z",
      "alt": 175.1
    },
    {
      "lat": 41.9401336,
      "lon": -82.5159289,
      "t": "2025-07-27T15:49:02Z",
      "alt": 175.0
    },
    {
      "lat": 41.9400912,
      "lon": -82.5159142,
      "t": "2025-07-27T15:49:12Z",
      "alt": 174.9
    },
    {
      "lat": 41.9400723,
      "lon": -82.515931,
      "t": "2025-07-27T15:49:22Z",
      "alt": 174.8
    },
    {
      "lat": 41.9400102,
      "lon": -82.515988,
      "t": "2025-07-27T15:49:32Z",
      "alt": 174.7
    },
    {
      "lat": 41.9399781,
      "lon": -82.5160931,
      "t": "2025-07-27T15:49:42Z",
      "alt": 174.5
    },
    {
      "lat": 41.9399269,
      "lon": -82.5161247,
      "t": "2025-07-27T15:49:52Z",
      "alt": 174.4
    },
    {
      "lat": 41.9399034,
      "lon": -82.5161925,
      "t": "2025-07-27T15:50:02Z",
      "alt": 174.2
    },
    {
      "lat": 41.9399532,
      "lon": -82.5163349,
      "t": "2025-07-27T15:50:12Z",
      "alt": 174.1
    },
    {
      "lat": 41.9399315,
      "lon": -82.5163703,
      "t": "2025-07-27T15:50:22Z",
      "alt": 174.0
    },
    {
      "lat": 41.9399449,
      "lon": -82.5164168,
      "t": "2025-07-27T15:50:32Z",
      "alt": 173.8
    },
    {
      "lat": 41.9399169,
      "lon": -82.5164776,
      "t": "2025-07-27T15:50:42Z",
      "alt": 173.7
    },
    {
      "lat": 41.9398454,
      "lon": -82.5165207,
      "t": "2025-07-27T15:50:52Z",
      "alt": 173.5
    },
    {
      "lat": 41.9398243,
      "lon": -82.5164693,
      "t": "2025-07-27T15:51:03Z",
      "alt": 173.4
    },
    {
      "lat": 41.9398058,
      "lon": -82.5165538,
      "t": "2025-07-27T15:51:13Z",
      "alt": 173.2
    },
    {
      "lat": 41.9396528,
      "lon": -82.5165601,
      "t": "2025-07-27T15:51:23Z",
      "alt": 173.1
    },
    {
      "lat": 41.9396543,
      "lon": -82.5165444,
      "t": "2025-07-27T15:51:33Z",
      "alt": 173.0
    },
    {
      "lat": 41.9395998,
      "lon": -82.5165357,
      "t": "2025-07-27T15:51:43Z",
      "alt": 172.9
    },
    {
      "lat": 41.9395921,
      "lon": -82.5164348,
      "t": "2025-07-27T15:51:53Z",
      "alt": 172.8
    },
    {
      "lat": 41.9396065,
      "lon": -82.5163694,
      "t": "2025-07-27T15:52:03Z",
      "alt": 172.7
    },
    {
      "lat": 41.9396697,
      "lon": -82.5163879,
      "t": "2025-07-27T15:52:13Z",
      "alt": 172.6
    },
    {
      "lat": 41.9396172,
      "lon": -82.5163077,
      "t": "2025-07-27T15:52:23Z",
      "alt": 172.6
    },
    {
      "lat": 41.9395807,
      "lon": -82.5162591,
      "t": "2025-07-27T15:52:33Z",
      "alt": 172.5
    },
    {
      "lat": 41.9395658,
      "lon": -82.516248,
      "t": "2025-07-27T15:52:43Z",
      "alt": 172.5
    },
    {
      "lat": 41.9395203,
      "lon": -82.5161773,
      "t": "2025-07-27T15:52:53Z",
      "alt": 172.5
    },
    {
      "lat": 41.9394794,
      "lon": -82.5162295,
      "t": "2025-07-27T15:53:04Z",
      "alt": 172.5
    },
    {
      "lat": 41.9394531,
      "lon": -82.5162495,
      "t": "2025-07-27T15:53:14Z",
      "alt": 172.5
    },
    {
      "lat": 41.939507,
      "lon": -82.5162677,
      "t": "2025-07-27T15:53:24Z",
      "alt": 172.5
    },
    {
      "lat": 41.939352,
      "lon": -82.5164497,
      "t": "2025-07-27T15:53:34Z",
      "alt": 172.6
    },
    {
      "lat": 41.9392718,
      "lon": -82.5166056,
      "t": "2025-07-27T15:53:44Z",
      "alt": 172.6
    },
    {
      "lat": 41.9391393,
      "lon": -82.5165753,
      "t": "2025-07-27T15:53:54Z",
      "alt": 172.7
    },
    {
      "lat": 41.9390454,
      "lon": -82.5164971,
      "t": "2025-07-27T15:54:04Z",
      "alt": 172.8
    },
    {
      "lat": 41.9390316,
      "lon": -82.5165087,
      "t": "2025-07-27T15:54:14Z",
      "alt": 172.9
    },
    {
      "lat": 41.9389597,
      "lon": -82.5165343,
      "t": "2025-07-27T15:54:24Z",
      "alt": 173.0
    },
    {
      "lat": 41.9389248,
      "lon": -82.5164974,
      "t": "2025-07-27T15:54:34Z",
      "alt": 173.1
    },
    {
      "lat": 41.9388676,
      "lon": -82.5165182,
      "t": "2025-07-27T15:54:44Z",
      "alt": 173.2
    },
    {
      "lat": 41.9387526,
      "lon": -82.5164186,
      "t": "2025-07-27T15:54:54Z",
      "alt": 173.4
    },
    {
      "lat": 41.9387186,
      "lon": -82.5163807,
      "t": "2025-07-27T15:55:05Z",
      "alt": 173.5
    },
    {
      "lat": 41.9386682,
      "lon": -82.5163933,
      "t": "2025-07-27T15:55:15Z",
      "alt": 173.7
    },
    {
      "lat": 41.9386659,
      "lon": -82.5162677,
      "t": "2025-07-27T15:55:25Z",
      "alt": 173.8
    },
    {
      "lat": 41.9386414,
      "lon": -82.5162214,
      "t": "2025-07-27T15:55:35Z",
      "alt": 174.0
    },
    {
      "lat": 41.9385314,
      "lon": -82.5161655,
      "t": "2025-07-27T15:55:45Z",
      "alt": 174.1
    },
    {
      "lat": 41.9385821,
      "lon": -82.5161252,
      "t": "2025-07-27T15:55:55Z",
      "alt": 174.2
    },
    {
      "lat": 41.9385741,
      "lon": -82.5160867,
      "t": "2025-07-27T15:56:05Z",
      "alt": 174.4
    },
    {
      "lat": 41.9385431,
      "lon": -82.5160914,
      "t": "2025-07-27T15:56:15Z",
      "alt": 174.5
    },
    {
      "lat": 41.9385296,
      "lon": -82.5160062,
      "t": "2025-07-27T15:56:25Z",
      "alt": 174.7
    },
    {
      "lat": 41.938516,
      "lon": -82.5158588,
      "t": "2025-07-27T15:56:35Z",
      "alt": 174.8
    },
    {
      "lat": 41.9385459,
      "lon": -82.5158839,
      "t": "2025-07-27T15:56:45Z",
      "alt": 174.9
    },
    {
      "lat": 41.9386929,
      "lon": -82.5157642,
      "t": "2025-07-27T15:56:55Z",
      "alt": 175.0
    },
    {
      "lat": 41.9386847,
      "lon": -82.5157382,
      "t": "2025-07-27T15:57:06Z",
      "alt": 175.1
    },
    {
      "lat": 41.9387423,
      "lon": -82.5156908,
      "t": "2025-07-27T15:57:16Z",
      "alt": 175.2
    },
    {
      "lat": 41.9387048,
      "lon": -82.5155616,
      "t": "2025-07-27T15:57:26Z",
      "alt": 175.3
    },
    {
      "lat": 41.9387277,
      "lon": -82.5154866,
      "t": "2025-07-27T15:57:36Z",
      "alt": 175.4
    },
    {
      "lat": 41.9386638,
      "lon": -82.5153099,
      "t": "2025-07-27T15:57:46Z",
      "alt": 175.4
    },
    {
      "lat": 41.9386673,
      "lon": -82.5152933,
      "t": "2025-07-27T15:57:56Z",
      "alt": 175.5
    },
    {
      "lat": 41.9387226,
      "lon": -82.5152405,
      "t": "2025-07-27T15:58:06Z",
      "alt": 175.5
    },
    {
      "lat": 41.9388039,
      "lon": -82.5151178,
      "t": "2025-07-27T15:58:16Z",
      "alt": 175.5
    },
    {
      "lat": 41.9387928,
      "lon": -82.5150995,
      "t": "2025-07-27T15:58:26Z",
      "alt": 175.5
    },
    {
      "lat": 41.938814,
      "lon": -82.5151279,
      "t": "2025-07-27T15:58:36Z",
      "alt": 175.5
    },
    {
      "lat": 41.9387624,
      "lon": -82.5150156,
      "t": "2025-07-27T15:58:46Z",
      "alt": 175.4
    },
    {
      "lat": 41.9388016,
      "lon": -82.5149814,
      "t": "2025-07-27T15:58:56Z",
      "alt": 175.4
    },
    {
      "lat": 41.9388409,
      "lon": -82.5149573,
      "t": "2025-07-27T15:59:07Z",
      "alt": 175.3
    },
    {
      "lat": 41.9388536,
      "lon": -82.514918,
      "t": "2025-07-27T15:59:17Z",
      "alt": 175.3
    },
    {
      "lat": 41.9389015,
      "lon": -82.5148752,
      "t": "2025-07-27T15:59:27Z",
      "alt": 175.2
    },
    {
      "lat": 41.9389793,
      "lon": -82.5148713,
      "t": "2025-07-27T15:59:37Z",
      "alt": 175.1
    },
    {
      "lat": 41.9389669,
      "lon": -82.5148377,
      "t": "2025-07-27T15:59:47Z",
      "alt": 175.0
    },
    {
      "lat": 41.9390226,
      "lon": -82.5148686,
      "t": "2025-07-27T15:59:57Z",
      "alt": 174.8
    },
    {
      "lat": 41.9390661,
      "lon": -82.514881,
      "t": "2025-07-27T16:00:07Z",
      "alt": 174.7
    },
    {
      "lat": 41.9391416,
      "lon": -82.5149465,
      "t": "2025-07-27T16:00:17Z",
      "alt": 174.6
    },
    {
      "lat": 41.9392333,
      "lon": -82.5149045,
      "t": "2025-07-27T16:00:27Z",
      "alt": 174.4
    },
    {
      "lat": 41.9392817,
      "lon": -82.5149783,
      "t": "2025-07-27T16:00:37Z",
      "alt": 174.3
    },
    {
      "lat": 41.9393961,
      "lon": -82.5148698,
      "t": "2025-07-27T16:00:47Z",
      "alt": 174.1
    },
    {
      "lat": 41.9394478,
      "lon": -82.5149093,
      "t": "2025-07-27T16:00:58Z",
      "alt": 174.0
    }
  ],
  "parks": [
    {
      "name": "POINT PELEE NATIONAL PARK OF CANADA",
      "source": "on_federal_parks.geojson"
    }
  ]
}
